shopdesk/__init__.py
shopdesk/main.py
shopdesk/scheduler.py
shopdesk/controllers/__init__.py
shopdesk/controllers/admin.py
shopdesk/controllers/base.py
shopdesk/models/__init__.py
shopdesk/models/order.py
shopdesk/test/__init__.py
shopdesk/test/order.py
shopdesk-0.1.1.dist-info/top_level.txt
shopdesk-0.1.1.dist-info/METADATA
shopdesk-0.1.1.dist-info/DESCRIPTION.rst
shopdesk-0.1.1.dist-info/metadata.json
shopdesk-0.1.1.dist-info/WHEEL
shopdesk-0.1.1.dist-info/RECORD
